ampyobs/__init__.py
ampyobs/logger.py
ampyobs/metrics.py
ampyobs/obs.py
ampyobs/propagation.py
ampyobs/tracing.py
ampyobs-0.0.2.dist-info/METADATA
ampyobs-0.0.2.dist-info/WHEEL
ampyobs-0.0.2.dist-info/top_level.txt
ampyobs-0.0.2.dist-info/RECORD
