Metadata-Version: 2.4
Name: ampyobs
Version: 0.0.2
Summary: Ampy Observability SDK (Python) — logs, metrics, tracing
Author: AmpyFin
Project-URL: Homepage, https://github.com/AmpyFin/ampy-observability
Requires-Python: >=3.10
Requires-Dist: opentelemetry-api>=1.22.0
Requires-Dist: opentelemetry-sdk>=1.22.0
Requires-Dist: opentelemetry-exporter-otlp>=1.22.0
